{
 "version": 1,
 "key_columns": [
  "relation_id"
 ],
 "by_key": {
  "110645@8_26-110645@8_17": {
   "is_correct": true
  },
  "27078@15_20-27078@15_13": {
   "is_correct": false
  },
  "143008@34_10-143008@34_13": {
   "is_correct": false
  },
  "107943@14_12-107943@14_2": {
   "is_correct": false
  },
  "147788@31_16-147788@31_29": {
   "is_correct": false
  },
  "46984@42_0-46984@42_19": {
   "is_correct": false
  },
  "22906@13_15-22906@13_0": {
   "is_correct": false
  },
  "106205@19_21-106205@19_19": {
   "is_correct": false
  },
  "14857@10_4-14857@10_0": {
   "is_correct": true
  },
  "134574@5_13-134574@5_3": {
   "is_correct": false
  },
  "135549@31_27-135549@31_39": {
   "is_correct": false
  },
  "15095@42_10-15095@42_0": {
   "is_correct": false
  },
  "41614@21_30-41614@21_23": {
   "is_correct": false
  },
  "124725@2_34-124725@2_7": {
   "is_correct": false
  },
  "45172@25_28-45172@25_22": {
   "is_correct": false
  },
  "103150@21_34-103150@21_74": {
   "is_correct": false
  },
  "18789@64_27-18789@64_20": {
   "is_correct": false
  },
  "135683@28_24-135683@28_17": {
   "is_correct": false
  },
  "64529@86_23-64529@86_12": {
   "is_correct": false
  },
  "108567@37_16-108567@37_18": {
   "is_correct": false
  },
  "33710@0_21-33710@0_10": {
   "is_correct": true
  },
  "82383@25_61-82383@25_52": {
   "is_correct": false
  },
  "111256@14_18-111256@14_29": {
   "is_correct": false
  },
  "32196@22_19-32196@22_13": {
   "is_correct": true
  },
  "13553@21_35-13553@21_15": {
   "is_correct": false
  },
  "72549@33_58-72549@33_84": {
   "is_correct": false
  },
  "101715@5_16-101715@5_9": {
   "is_correct": false
  },
  "12152@27_38-12152@27_19": {
   "is_correct": false
  },
  "140708@9_21-140708@9_28": {
   "is_correct": false
  },
  "132697@4_20-132697@4_9": {
   "is_correct": false
  },
  "112624@8_60-112624@8_38": {
   "is_correct": false
  },
  "28498@7_7-28498@7_24": {
   "is_correct": false
  },
  "62159@34_13-62159@34_16": {
   "is_correct": false
  },
  "134523@38_29-134523@38_23": {
   "is_correct": false
  },
  "113832@33_10-113832@33_8": {
   "is_correct": false
  },
  "95193@9_30-95193@9_21": {
   "is_correct": false
  },
  "135626@1_1-135626@1_16": {
   "is_correct": false
  },
  "87407@56_74-87407@56_67": {
   "is_correct": false
  },
  "34215@40_89-34215@40_114": {
   "is_correct": false
  },
  "36745@34_35-36745@34_22": {
   "is_correct": false
  },
  "143079@36_44-143079@36_33": {
   "is_correct": false
  },
  "48899@3_1-48899@3_31": {
   "is_correct": true
  },
  "90491@47_0-90491@47_18": {
   "is_correct": false
  },
  "53484@39_48-53484@39_31": {
   "is_correct": false
  },
  "9287@8_29-9287@8_22": {
   "is_correct": false
  },
  "60823@33_47-60823@33_26": {
   "is_correct": false
  },
  "35870@26_17-35870@26_9": {
   "is_correct": false
  },
  "64529@80_22-64529@80_33": {
   "is_correct": false
  },
  "23618@28_58-23618@28_21": {
   "is_correct": false
  },
  "46984@19_15-46984@19_0": {
   "is_correct": false
  },
  "150008@34_8-150008@34_24": {
   "is_correct": false
  },
  "21069@39_0-21069@39_8": {
   "is_correct": false
  },
  "149371@43_15-149371@43_21": {
   "is_correct": false
  },
  "154431@2_12-154431@2_189": {
   "is_correct": false
  },
  "38740@43_25-38740@43_33": {
   "is_correct": false
  },
  "56584@22_60-56584@22_73": {
   "is_correct": false
  },
  "103874@45_23-103874@45_30": {
   "is_correct": false
  },
  "25360@55_43-25360@55_41": {
   "is_correct": false
  },
  "112624@26_18-112624@26_28": {
   "is_correct": false
  },
  "25360@59_26-25360@59_12": {
   "is_correct": false
  },
  "139064@44_35-139064@44_24": {
   "is_correct": false
  },
  "131068@31_2-131068@31_0": {
   "is_correct": false
  },
  "136165@22_102-136165@22_61": {
   "is_correct": false
  },
  "38603@20_36-38603@20_50": {
   "is_correct": false
  },
  "56239@7_69-56239@7_48": {
   "is_correct": false
  },
  "147788@36_50-147788@36_45": {
   "is_correct": false
  },
  "154470@0_12-154470@0_15": {
   "is_correct": false
  },
  "56822@16_52-56822@16_34": {
   "is_correct": false
  },
  "102122@21_50-102122@21_17": {
   "is_correct": false
  },
  "1938@37_58-1938@37_23": {
   "is_correct": false
  },
  "98134@16_19-98134@16_0": {
   "is_correct": false
  },
  "21069@39_4-21069@39_14": {
   "is_correct": false
  },
  "38897@11_23-38897@11_6": {
   "is_correct": false
  },
  "139064@44_31-139064@44_17": {
   "is_correct": false
  },
  "39154@3_65-39154@3_56": {
   "is_correct": false
  },
  "23521@5_10-23521@5_8": {
   "is_correct": false
  },
  "70210@0_6-70210@0_41": {
   "is_correct": false
  },
  "139064@44_27-139064@44_39": {
   "is_correct": false
  },
  "71715@79_0-71715@79_2": {
   "is_correct": false
  },
  "23521@7_23-23521@7_21": {
   "is_correct": false
  },
  "125840@50_44-125840@50_2": {
   "is_correct": false
  },
  "136165@22_102-136165@22_160": {
   "is_correct": false
  },
  "43951@28_50-43951@28_44": {
   "is_correct": false
  },
  "1986@24_25-1986@24_22": {
   "is_correct": false
  },
  "25360@60_18-25360@60_36": {
   "is_correct": false
  },
  "39608@1_2-39608@1_8": {
   "is_correct": false
  },
  "3921@32_9-3921@32_6": {
   "is_correct": false
  },
  "141290@6_0-141290@6_22": {
   "is_correct": false
  },
  "79572@23_37-79572@23_47": {
   "is_correct": false
  },
  "136165@22_131-136165@22_61": {
   "is_correct": false
  },
  "143079@36_12-143079@36_53": {
   "is_correct": false
  },
  "77342@4_9-77342@4_6": {
   "is_correct": false
  },
  "24079@17_3-24079@17_0": {
   "is_correct": false
  },
  "34215@40_83-34215@40_86": {
   "is_correct": false
  },
  "15241@45_0-15241@45_28": {
   "is_correct": false
  },
  "135441@22_44-135441@22_25": {
   "is_correct": false
  },
  "149548@2_30-149548@2_26": {
   "is_correct": false
  },
  "48432@10_0-48432@10_4": {
   "is_correct": false
  },
  "136165@22_32-136165@22_34": {
   "is_correct": false
  },
  "122380@11_21-122380@11_29": {
   "is_correct": false
  },
  "1316@8_17-1316@8_14": {
   "is_correct": false
  },
  "72549@33_84-72549@33_90": {
   "is_correct": false
  },
  "93681@30_45-93681@30_10": {
   "is_correct": false
  }
 }
}